jax/geneweaver/core/__init__.py
jax/geneweaver/core/config.py
jax/geneweaver/core/config_class.py
jax/geneweaver/core/enum.py
jax/geneweaver/core/exc.py
jax/geneweaver/core/schema/__init__.py
jax/geneweaver/core/schema/gene.py
jax/geneweaver/core/schema/geneset.py
jax/geneweaver/core/schema/group.py
jax/geneweaver/core/schema/legacy_api.py
jax/geneweaver/core/schema/project.py
jax/geneweaver/core/schema/publication.py
jax/geneweaver/core/schema/stubgenerator.py
jax/geneweaver/core/schema/user.py
jax_geneweaver_core-0.0.6.dist-info/WHEEL
jax_geneweaver_core-0.0.6.dist-info/METADATA
jax_geneweaver_core-0.0.6.dist-info/RECORD
