Metadata-Version: 2.1
Name: jax-geneweaver-core
Version: 0.0.6
Summary: The core of the Jax-Geneweaver Python library
Author: Jax & Baylor Computational Sciences
Author-email: cssc@jax.org
Requires-Python: >=3.9,<4.0
Classifier: Programming Language :: Python :: 3
Classifier: Programming Language :: Python :: 3.9
Classifier: Programming Language :: Python :: 3.10
Classifier: Programming Language :: Python :: 3.11
Requires-Dist: pydantic[dotenv] (>=1.10.5,<2.0.0)
